[
    {
        "id":1001,
        "type":1,
        "name":"羽盾",
        "lv":1,
        "des":"受到攻击时|C:0x34E22C&T:10%|T:几率增加角色固定|C:0x34E22C&T:10000|T:点生命，间隔|C:0x34E22C&T:30|T:秒。",
        "nextId":1002,
        "talent":60101,
        "score":2000,
        "num":0,
        "consume":"299601_1"
    },
    {
        "id":1002,
        "type":1,
        "name":"羽盾",
        "lv":2,
        "des":"受到攻击时|C:0x34E22C&T:10%|T:几率增加角色固定|C:0x34E22C&T:25000|T:点生命，间隔|C:0x34E22C&T:30|T:秒。",
        "nextId":1003,
        "talent":60102,
        "score":6000,
        "num":0,
        "consume":"299601_2"
    },
    {
        "id":1003,
        "type":1,
        "name":"羽盾",
        "lv":3,
        "des":"受到攻击时|C:0x34E22C&T:10%|T:几率增加角色固定|C:0x34E22C&T:44000|T:点生命，间隔|C:0x34E22C&T:30|T:秒。",
        "nextId":1004,
        "talent":60103,
        "score":14000,
        "num":0,
        "consume":"299601_3"
    },
    {
        "id":1004,
        "type":1,
        "name":"羽盾",
        "lv":4,
        "des":"受到攻击时|C:0x34E22C&T:10%|T:几率增加角色固定|C:0x34E22C&T:65000|T:点生命，间隔|C:0x34E22C&T:30|T:秒。",
        "nextId":1005,
        "talent":60104,
        "score":26000,
        "num":0,
        "consume":"299601_4"
    },
    {
        "id":1005,
        "type":1,
        "name":"羽盾",
        "lv":5,
        "des":"受到攻击时|C:0x34E22C&T:10%|T:几率增加角色固定|C:0x34E22C&T:90000|T:点生命，间隔|C:0x34E22C&T:30|T:秒。",
        "nextId":1006,
        "talent":60105,
        "score":42000,
        "num":0,
        "consume":"299601_6"
    },
    {
        "id":1006,
        "type":1,
        "name":"羽盾",
        "lv":6,
        "des":"受到攻击时|C:0x34E22C&T:10%|T:几率增加角色固定|C:0x34E22C&T:120000|T:点生命，间隔|C:0x34E22C&T:30|T:秒。",
        "nextId":1007,
        "talent":60106,
        "score":66000,
        "num":0,
        "consume":"299601_8"
    },
    {
        "id":1007,
        "type":1,
        "name":"羽盾",
        "lv":7,
        "des":"受到攻击时|C:0x34E22C&T:10%|T:几率增加角色固定|C:0x34E22C&T:160000|T:点生命，间隔|C:0x34E22C&T:30|T:秒。",
        "nextId":1008,
        "talent":60107,
        "score":98000,
        "num":0,
        "consume":"299601_10"
    },
    {
        "id":1008,
        "type":1,
        "name":"羽盾",
        "lv":8,
        "des":"受到攻击时|C:0x34E22C&T:10%|T:几率增加角色固定|C:0x34E22C&T:200000|T:点生命，间隔|C:0x34E22C&T:30|T:秒。",
        "nextId":1009,
        "talent":60108,
        "score":138000,
        "num":0,
        "consume":"299601_12"
    },
    {
        "id":1009,
        "type":1,
        "name":"羽盾",
        "lv":9,
        "des":"受到攻击时|C:0x34E22C&T:10%|T:几率增加角色固定|C:0x34E22C&T:250000|T:点生命，间隔|C:0x34E22C&T:30|T:秒。",
        "nextId":1010,
        "talent":60109,
        "score":186000,
        "num":0,
        "consume":"299601_15"
    },
    {
        "id":1010,
        "type":1,
        "name":"羽盾",
        "lv":10,
        "des":"受到攻击时|C:0x34E22C&T:10%|T:几率增加角色固定|C:0x34E22C&T:300000|T:点生命，间隔|C:0x34E22C&T:30|T:秒。",
        "nextId":-1,
        "talent":60110,
        "score":246000,
        "num":0,
        "consume":"299601_0"
    },
    {
        "id":2001,
        "type":2,
        "name":"翼击",
        "lv":1,
        "des":"受到攻击时|C:0x34E22C&T:10%|T:几率，造成|C:0x34E22C&T:10000|T:点反击伤害，间隔|C:0x34E22C&T:30|T:秒。",
        "nextId":2002,
        "talent":60201,
        "score":2000,
        "num":0,
        "consume":"299602_1"
    },
    {
        "id":2002,
        "type":2,
        "name":"翼击",
        "lv":2,
        "des":"受到攻击时|C:0x34E22C&T:10%|T:几率，造成|C:0x34E22C&T:25000|T:点反击伤害，间隔|C:0x34E22C&T:30|T:秒。",
        "nextId":2003,
        "talent":60202,
        "score":6000,
        "num":0,
        "consume":"299602_2"
    },
    {
        "id":2003,
        "type":2,
        "name":"翼击",
        "lv":3,
        "des":"受到攻击时|C:0x34E22C&T:10%|T:几率，造成|C:0x34E22C&T:44000|T:点反击伤害，间隔|C:0x34E22C&T:30|T:秒。",
        "nextId":2004,
        "talent":60203,
        "score":14000,
        "num":0,
        "consume":"299602_3"
    },
    {
        "id":2004,
        "type":2,
        "name":"翼击",
        "lv":4,
        "des":"受到攻击时|C:0x34E22C&T:10%|T:几率，造成|C:0x34E22C&T:65000|T:点反击伤害，间隔|C:0x34E22C&T:30|T:秒。",
        "nextId":2005,
        "talent":60204,
        "score":26000,
        "num":0,
        "consume":"299602_4"
    },
    {
        "id":2005,
        "type":2,
        "name":"翼击",
        "lv":5,
        "des":"受到攻击时|C:0x34E22C&T:10%|T:几率，造成|C:0x34E22C&T:90000|T:点反击伤害，间隔|C:0x34E22C&T:30|T:秒。",
        "nextId":2006,
        "talent":60205,
        "score":42000,
        "num":0,
        "consume":"299602_6"
    },
    {
        "id":2006,
        "type":2,
        "name":"翼击",
        "lv":6,
        "des":"受到攻击时|C:0x34E22C&T:10%|T:几率，造成|C:0x34E22C&T:120000|T:点反击伤害，间隔|C:0x34E22C&T:30|T:秒。",
        "nextId":2007,
        "talent":60206,
        "score":66000,
        "num":0,
        "consume":"299602_8"
    },
    {
        "id":2007,
        "type":2,
        "name":"翼击",
        "lv":7,
        "des":"受到攻击时|C:0x34E22C&T:10%|T:几率，造成|C:0x34E22C&T:160000|T:点反击伤害，间隔|C:0x34E22C&T:30|T:秒。",
        "nextId":2008,
        "talent":60207,
        "score":98000,
        "num":0,
        "consume":"299602_10"
    },
    {
        "id":2008,
        "type":2,
        "name":"翼击",
        "lv":8,
        "des":"受到攻击时|C:0x34E22C&T:10%|T:几率，造成|C:0x34E22C&T:200000|T:点反击伤害，间隔|C:0x34E22C&T:30|T:秒。",
        "nextId":2009,
        "talent":60208,
        "score":138000,
        "num":0,
        "consume":"299602_12"
    },
    {
        "id":2009,
        "type":2,
        "name":"翼击",
        "lv":9,
        "des":"受到攻击时|C:0x34E22C&T:10%|T:几率，造成|C:0x34E22C&T:250000|T:点反击伤害，间隔|C:0x34E22C&T:30|T:秒。",
        "nextId":2010,
        "talent":60209,
        "score":186000,
        "num":0,
        "consume":"299602_15"
    },
    {
        "id":2010,
        "type":2,
        "name":"翼击",
        "lv":10,
        "des":"受到攻击时|C:0x34E22C&T:10%|T:几率，造成|C:0x34E22C&T:300000|T:点反击伤害，间隔|C:0x34E22C&T:30|T:秒。",
        "nextId":-1,
        "talent":60210,
        "score":246000,
        "num":0,
        "consume":"299602_0"
    },
    {
        "id":3001,
        "type":3,
        "name":"幻影",
        "lv":1,
        "des":"受到攻击时|C:0x34E22C&T:5%|T:几率进入幻影状态，增加自身闪避率提高|C:0x34E22C&T:40%|T:，持续|C:0x34E22C&T:3|T:秒，间隔|C:0x34E22C&T:1|T:分钟。",
        "nextId":3002,
        "talent":60301,
        "score":2000,
        "num":0,
        "consume":"299603_1"
    },
    {
        "id":3002,
        "type":3,
        "name":"幻影",
        "lv":2,
        "des":"受到攻击时|C:0x34E22C&T:5%|T:几率进入幻影状态，增加自身闪避率提高|C:0x34E22C&T:45%|T:，持续|C:0x34E22C&T:3|T:秒，间隔|C:0x34E22C&T:1|T:分钟。",
        "nextId":3003,
        "talent":60302,
        "score":6000,
        "num":0,
        "consume":"299603_2"
    },
    {
        "id":3003,
        "type":3,
        "name":"幻影",
        "lv":3,
        "des":"受到攻击时|C:0x34E22C&T:5%|T:几率进入幻影状态，增加自身闪避率提高|C:0x34E22C&T:50%|T:，持续|C:0x34E22C&T:3|T:秒，间隔|C:0x34E22C&T:1|T:分钟。",
        "nextId":3004,
        "talent":60303,
        "score":14000,
        "num":0,
        "consume":"299603_3"
    },
    {
        "id":3004,
        "type":3,
        "name":"幻影",
        "lv":4,
        "des":"受到攻击时|C:0x34E22C&T:5%|T:几率进入幻影状态，增加自身闪避率提高|C:0x34E22C&T:55%|T:，持续|C:0x34E22C&T:3|T:秒，间隔|C:0x34E22C&T:1|T:分钟。",
        "nextId":3005,
        "talent":60304,
        "score":26000,
        "num":0,
        "consume":"299603_4"
    },
    {
        "id":3005,
        "type":3,
        "name":"幻影",
        "lv":5,
        "des":"受到攻击时|C:0x34E22C&T:7%|T:几率进入幻影状态，增加自身闪避率提高|C:0x34E22C&T:60%|T:，持续|C:0x34E22C&T:3|T:秒，间隔|C:0x34E22C&T:1|T:分钟。",
        "nextId":3006,
        "talent":60305,
        "score":42000,
        "num":0,
        "consume":"299603_6"
    },
    {
        "id":3006,
        "type":3,
        "name":"幻影",
        "lv":6,
        "des":"受到攻击时|C:0x34E22C&T:7%|T:几率进入幻影状态，增加自身闪避率提高|C:0x34E22C&T:65%|T:，持续|C:0x34E22C&T:3|T:秒，间隔|C:0x34E22C&T:1|T:分钟。",
        "nextId":3007,
        "talent":60306,
        "score":66000,
        "num":0,
        "consume":"299603_8"
    },
    {
        "id":3007,
        "type":3,
        "name":"幻影",
        "lv":7,
        "des":"受到攻击时|C:0x34E22C&T:7%|T:几率进入幻影状态，增加自身闪避率提高|C:0x34E22C&T:70%|T:，持续|C:0x34E22C&T:3|T:秒，间隔|C:0x34E22C&T:1|T:分钟。",
        "nextId":3008,
        "talent":60307,
        "score":98000,
        "num":0,
        "consume":"299603_10"
    },
    {
        "id":3008,
        "type":3,
        "name":"幻影",
        "lv":8,
        "des":"受到攻击时|C:0x34E22C&T:10%|T:几率进入幻影状态，增加自身闪避率提高|C:0x34E22C&T:75%|T:，持续|C:0x34E22C&T:3|T:秒，间隔|C:0x34E22C&T:1|T:分钟。",
        "nextId":3009,
        "talent":60308,
        "score":138000,
        "num":0,
        "consume":"299603_12"
    },
    {
        "id":3009,
        "type":3,
        "name":"幻影",
        "lv":9,
        "des":"受到攻击时|C:0x34E22C&T:10%|T:几率进入幻影状态，增加自身闪避率提高|C:0x34E22C&T:80%|T:，持续|C:0x34E22C&T:3|T:秒，间隔|C:0x34E22C&T:1|T:分钟。",
        "nextId":3010,
        "talent":60309,
        "score":186000,
        "num":0,
        "consume":"299603_15"
    },
    {
        "id":3010,
        "type":3,
        "name":"幻影",
        "lv":10,
        "des":"受到攻击时|C:0x34E22C&T:10%|T:几率进入幻影状态，增加自身闪避率提高|C:0x34E22C&T:90%|T:，持续|C:0x34E22C&T:3|T:秒，间隔|C:0x34E22C&T:1|T:分钟。",
        "nextId":-1,
        "talent":60310,
        "score":246000,
        "num":0,
        "consume":"299603_0"
    },
    {
        "id":4001,
        "type":4,
        "name":"死亡审判",
        "lv":1,
        "des":"攻击时|C:0x34E22C&T:5%|T:几率使自身加害加深|C:0x34E22C&T:10%|T:，持续|C:0x34E22C&T:3|T:秒，间隔|C:0x34E22C&T:30|T:秒。",
        "nextId":4002,
        "talent":60401,
        "score":2000,
        "num":0,
        "consume":"299604_1"
    },
    {
        "id":4002,
        "type":4,
        "name":"死亡审判",
        "lv":2,
        "des":"攻击时|C:0x34E22C&T:5%|T:几率使自身加害加深|C:0x34E22C&T:12%|T:，持续|C:0x34E22C&T:3|T:秒，间隔|C:0x34E22C&T:30|T:秒。",
        "nextId":4003,
        "talent":60402,
        "score":6000,
        "num":0,
        "consume":"299604_2"
    },
    {
        "id":4003,
        "type":4,
        "name":"死亡审判",
        "lv":3,
        "des":"攻击时|C:0x34E22C&T:5%|T:几率使自身加害加深|C:0x34E22C&T:14%|T:，持续|C:0x34E22C&T:3|T:秒，间隔|C:0x34E22C&T:30|T:秒。",
        "nextId":4004,
        "talent":60403,
        "score":14000,
        "num":0,
        "consume":"299604_3"
    },
    {
        "id":4004,
        "type":4,
        "name":"死亡审判",
        "lv":4,
        "des":"攻击时|C:0x34E22C&T:5%|T:几率使自身加害加深|C:0x34E22C&T:16%|T:，持续|C:0x34E22C&T:4|T:秒，间隔|C:0x34E22C&T:30|T:秒。",
        "nextId":4005,
        "talent":60404,
        "score":26000,
        "num":0,
        "consume":"299604_4"
    },
    {
        "id":4005,
        "type":4,
        "name":"死亡审判",
        "lv":5,
        "des":"攻击时|C:0x34E22C&T:7%|T:几率使自身加害加深|C:0x34E22C&T:18%|T:，持续|C:0x34E22C&T:4|T:秒，间隔|C:0x34E22C&T:30|T:秒。",
        "nextId":4006,
        "talent":60405,
        "score":42000,
        "num":0,
        "consume":"299604_6"
    },
    {
        "id":4006,
        "type":4,
        "name":"死亡审判",
        "lv":6,
        "des":"攻击时|C:0x34E22C&T:7%|T:几率使自身加害加深|C:0x34E22C&T:20%|T:，持续|C:0x34E22C&T:4|T:秒，间隔|C:0x34E22C&T:30|T:秒。",
        "nextId":4007,
        "talent":60406,
        "score":66000,
        "num":0,
        "consume":"299604_8"
    },
    {
        "id":4007,
        "type":4,
        "name":"死亡审判",
        "lv":7,
        "des":"攻击时|C:0x34E22C&T:7%|T:几率使自身加害加深|C:0x34E22C&T:22%|T:，持续|C:0x34E22C&T:5|T:秒，间隔|C:0x34E22C&T:30|T:秒。",
        "nextId":4008,
        "talent":60407,
        "score":98000,
        "num":0,
        "consume":"299604_10"
    },
    {
        "id":4008,
        "type":4,
        "name":"死亡审判",
        "lv":8,
        "des":"攻击时|C:0x34E22C&T:10%|T:几率使自身加害加深|C:0x34E22C&T:24%|T:，持续|C:0x34E22C&T:5|T:秒，间隔|C:0x34E22C&T:30|T:秒。",
        "nextId":4009,
        "talent":60408,
        "score":138000,
        "num":0,
        "consume":"299604_12"
    },
    {
        "id":4009,
        "type":4,
        "name":"死亡审判",
        "lv":9,
        "des":"攻击时|C:0x34E22C&T:10%|T:几率使自身加害加深|C:0x34E22C&T:26%|T:，持续|C:0x34E22C&T:5|T:秒，间隔|C:0x34E22C&T:30|T:秒。",
        "nextId":4010,
        "talent":60409,
        "score":186000,
        "num":0,
        "consume":"299604_15"
    },
    {
        "id":4010,
        "type":4,
        "name":"死亡审判",
        "lv":10,
        "des":"攻击时|C:0x34E22C&T:10%|T:几率使自身加害加深|C:0x34E22C&T:30%|T:，持续|C:0x34E22C&T:5|T:秒，间隔|C:0x34E22C&T:30|T:秒。",
        "nextId":-1,
        "talent":60410,
        "score":246000,
        "num":0,
        "consume":"299604_0"
    },
    {
        "id":5001,
        "type":5,
        "name":"星辰之力",
        "lv":1,
        "des":"受到攻击时|C:0x34E22C&T:5%|T:几率使自身伤害减免|C:0x34E22C&T:10%|T:，持续|C:0x34E22C&T:3|T:秒，间隔|C:0x34E22C&T:30|T:秒。",
        "nextId":5002,
        "talent":60501,
        "score":2000,
        "num":0,
        "consume":"299605_1"
    },
    {
        "id":5002,
        "type":5,
        "name":"星辰之力",
        "lv":2,
        "des":"受到攻击时|C:0x34E22C&T:5%|T:几率使自身伤害减免|C:0x34E22C&T:12%|T:，持续|C:0x34E22C&T:3|T:秒，间隔|C:0x34E22C&T:30|T:秒。",
        "nextId":5003,
        "talent":60502,
        "score":6000,
        "num":0,
        "consume":"299605_2"
    },
    {
        "id":5003,
        "type":5,
        "name":"星辰之力",
        "lv":3,
        "des":"受到攻击时|C:0x34E22C&T:5%|T:几率使自身伤害减免|C:0x34E22C&T:14%|T:，持续|C:0x34E22C&T:3|T:秒，间隔|C:0x34E22C&T:30|T:秒。",
        "nextId":5004,
        "talent":60503,
        "score":14000,
        "num":0,
        "consume":"299605_3"
    },
    {
        "id":5004,
        "type":5,
        "name":"星辰之力",
        "lv":4,
        "des":"受到攻击时|C:0x34E22C&T:5%|T:几率使自身伤害减免|C:0x34E22C&T:16%|T:，持续|C:0x34E22C&T:4|T:秒，间隔|C:0x34E22C&T:30|T:秒。",
        "nextId":5005,
        "talent":60504,
        "score":26000,
        "num":0,
        "consume":"299605_4"
    },
    {
        "id":5005,
        "type":5,
        "name":"星辰之力",
        "lv":5,
        "des":"受到攻击时|C:0x34E22C&T:7%|T:几率使自身伤害减免|C:0x34E22C&T:18%|T:，持续|C:0x34E22C&T:4|T:秒，间隔|C:0x34E22C&T:30|T:秒。",
        "nextId":5006,
        "talent":60505,
        "score":42000,
        "num":0,
        "consume":"299605_6"
    },
    {
        "id":5006,
        "type":5,
        "name":"星辰之力",
        "lv":6,
        "des":"受到攻击时|C:0x34E22C&T:7%|T:几率使自身伤害减免|C:0x34E22C&T:20%|T:，持续|C:0x34E22C&T:4|T:秒，间隔|C:0x34E22C&T:30|T:秒。",
        "nextId":5007,
        "talent":60506,
        "score":66000,
        "num":0,
        "consume":"299605_8"
    },
    {
        "id":5007,
        "type":5,
        "name":"星辰之力",
        "lv":7,
        "des":"受到攻击时|C:0x34E22C&T:7%|T:几率使自身伤害减免|C:0x34E22C&T:22%|T:，持续|C:0x34E22C&T:5|T:秒，间隔|C:0x34E22C&T:30|T:秒。",
        "nextId":5008,
        "talent":60507,
        "score":98000,
        "num":0,
        "consume":"299605_10"
    },
    {
        "id":5008,
        "type":5,
        "name":"星辰之力",
        "lv":8,
        "des":"受到攻击时|C:0x34E22C&T:10%|T:几率使自身伤害减免|C:0x34E22C&T:24%|T:，持续|C:0x34E22C&T:5|T:秒，间隔|C:0x34E22C&T:30|T:秒。",
        "nextId":5009,
        "talent":60508,
        "score":138000,
        "num":0,
        "consume":"299605_12"
    },
    {
        "id":5009,
        "type":5,
        "name":"星辰之力",
        "lv":9,
        "des":"受到攻击时|C:0x34E22C&T:10%|T:几率使自身伤害减免|C:0x34E22C&T:26%|T:，持续|C:0x34E22C&T:5|T:秒，间隔|C:0x34E22C&T:30|T:秒。",
        "nextId":5010,
        "talent":60509,
        "score":186000,
        "num":0,
        "consume":"299605_15"
    },
    {
        "id":5010,
        "type":5,
        "name":"星辰之力",
        "lv":10,
        "des":"受到攻击时|C:0x34E22C&T:10%|T:几率使自身伤害减免|C:0x34E22C&T:30%|T:，持续|C:0x34E22C&T:5|T:秒，间隔|C:0x34E22C&T:30|T:秒。",
        "nextId":-1,
        "talent":60510,
        "score":246000,
        "num":0,
        "consume":"299605_0"
    },
    {
        "id":6001,
        "type":6,
        "name":"生命仲裁",
        "lv":1,
        "des":"濒死时，有|C:0x34E22C&T:10%|T:几率触发，立即回复|C:0x34E22C&T:10%|T:生命值。",
        "nextId":6002,
        "talent":60601,
        "score":2000,
        "num":0,
        "consume":"299606_1"
    },
    {
        "id":6002,
        "type":6,
        "name":"生命仲裁",
        "lv":2,
        "des":"濒死时，有|C:0x34E22C&T:12%|T:几率触发，立即回复|C:0x34E22C&T:12%|T:生命值。",
        "nextId":6003,
        "talent":60602,
        "score":6000,
        "num":0,
        "consume":"299606_2"
    },
    {
        "id":6003,
        "type":6,
        "name":"生命仲裁",
        "lv":3,
        "des":"濒死时，有|C:0x34E22C&T:14%|T:几率触发，立即回复|C:0x34E22C&T:14%|T:生命值。",
        "nextId":6004,
        "talent":60603,
        "score":14000,
        "num":0,
        "consume":"299606_3"
    },
    {
        "id":6004,
        "type":6,
        "name":"生命仲裁",
        "lv":4,
        "des":"濒死时，有|C:0x34E22C&T:16%|T:几率触发，立即回复|C:0x34E22C&T:16%|T:生命值。",
        "nextId":6005,
        "talent":60604,
        "score":26000,
        "num":0,
        "consume":"299606_4"
    },
    {
        "id":6005,
        "type":6,
        "name":"生命仲裁",
        "lv":5,
        "des":"濒死时，有|C:0x34E22C&T:18%|T:几率触发，立即回复|C:0x34E22C&T:18%|T:生命值。",
        "nextId":6006,
        "talent":60605,
        "score":42000,
        "num":0,
        "consume":"299606_6"
    },
    {
        "id":6006,
        "type":6,
        "name":"生命仲裁",
        "lv":6,
        "des":"濒死时，有|C:0x34E22C&T:20%|T:几率触发，立即回复|C:0x34E22C&T:21%|T:生命值。",
        "nextId":6007,
        "talent":60606,
        "score":66000,
        "num":0,
        "consume":"299606_8"
    },
    {
        "id":6007,
        "type":6,
        "name":"生命仲裁",
        "lv":7,
        "des":"濒死时，有|C:0x34E22C&T:22%|T:几率触发，立即回复|C:0x34E22C&T:24%|T:生命值。",
        "nextId":6008,
        "talent":60607,
        "score":98000,
        "num":0,
        "consume":"299606_10"
    },
    {
        "id":6008,
        "type":6,
        "name":"生命仲裁",
        "lv":8,
        "des":"濒死时，有|C:0x34E22C&T:24%|T:几率触发，立即回复|C:0x34E22C&T:27%|T:生命值。",
        "nextId":6009,
        "talent":60608,
        "score":138000,
        "num":0,
        "consume":"299606_12"
    },
    {
        "id":6009,
        "type":6,
        "name":"生命仲裁",
        "lv":9,
        "des":"濒死时，有|C:0x34E22C&T:27%|T:几率触发，立即回复|C:0x34E22C&T:30%|T:生命值。",
        "nextId":6010,
        "talent":60609,
        "score":186000,
        "num":0,
        "consume":"299606_15"
    },
    {
        "id":6010,
        "type":6,
        "name":"生命仲裁",
        "lv":10,
        "des":"濒死时，有|C:0x34E22C&T:30%|T:几率触发，立即回复|C:0x34E22C&T:35%|T:生命值。",
        "nextId":-1,
        "talent":60610,
        "score":246000,
        "num":0,
        "consume":"299606_0"
    }
]