{"adornmentnpc_1":{"property":{"modelId":8002,"name":"Flying Butterfly"},"refId":"adornmentnpc_1"},"adornmentnpc_2":{"property":{"modelId":8003,"name":"Hovering Butterfly"},"refId":"adornmentnpc_2"},"adornmentnpc_3":{"property":{"modelId":8004,"name":"Stationary Butterfly"},"refId":"adornmentnpc_3"},"adornmentnpc_4":{"property":{"modelId":8005,"name":"Narrow Water Wave"},"refId":"adornmentnpc_4"},"adornmentnpc_5":{"property":{"modelId":8006,"name":"Wide Water Wave"},"refId":"adornmentnpc_5"},"adornmentnpc_6":{"property":{"modelId":8007,"name":"Mass Falling Leaves"},"refId":"adornmentnpc_6"},"adornmentnpc_7":{"property":{"modelId":8008,"name":"Single Falling Leaf"},"refId":"adornmentnpc_7"},"adornmentnpc_8":{"property":{"modelId":8009,"name":"Light Beam"},"refId":"adornmentnpc_8"},"adornmentnpc_9":{"property":{"modelId":8010,"name":"Flame"},"refId":"adornmentnpc_9"}}