{"file":"uiMain_activityIcon.png","frames":{
"main_icon_xinyue":{"x":463,"y":259,"w":74,"h":83,"offX":0,"offY":2,"sourceW":74,"sourceH":85},
"img_activity_red":{"x":973,"y":1,"w":24,"h":23,"offX":0,"offY":0,"sourceW":24,"sourceH":24},
"main_crossbattle":{"x":486,"y":1,"w":82,"h":85,"offX":0,"offY":0,"sourceW":82,"sourceH":85},
"main_icon_activity":{"x":226,"y":261,"w":68,"h":85,"offX":6,"offY":0,"sourceW":74,"sourceH":85},
"main_icon_attestation":{"x":381,"y":260,"w":74,"h":82,"offX":0,"offY":0,"sourceW":74,"sourceH":85},
"main_icon_dayChongZhi":{"x":682,"y":172,"w":74,"h":85,"offX":0,"offY":0,"sourceW":74,"sourceH":85},
"main_icon_dianjing":{"x":910,"y":175,"w":74,"h":83,"offX":0,"offY":2,"sourceW":74,"sourceH":85},
"main_icon_fanchenmi":{"x":539,"y":339,"w":67,"h":84,"offX":3,"offY":1,"sourceW":74,"sourceH":85},
"main_icon_firstPlayer":{"x":539,"y":259,"w":78,"h":78,"offX":0,"offY":0,"sourceW":78,"sourceH":78},
"main_icon_firstRecharge":{"x":920,"y":342,"w":70,"h":77,"offX":1,"offY":1,"sourceW":78,"sourceH":78},
"main_icon_guanzhu":{"x":438,"y":344,"w":63,"h":77,"offX":6,"offY":8,"sourceW":74,"sourceH":85},
"main_icon_hatch":{"x":79,"y":262,"w":69,"h":82,"offX":5,"offY":3,"sourceW":74,"sourceH":85},
"main_icon_hefu_activity":{"x":606,"y":172,"w":74,"h":85,"offX":0,"offY":0,"sourceW":74,"sourceH":85},
"main_icon_kefu":{"x":847,"y":260,"w":71,"h":84,"offX":7,"offY":1,"sourceW":82,"sourceH":85},
"main_icon_limitTime":{"x":1,"y":286,"w":76,"h":75,"offX":2,"offY":3,"sourceW":78,"sourceH":78},
"main_icon_mall":{"x":153,"y":261,"w":71,"h":82,"offX":0,"offY":3,"sourceW":74,"sourceH":85},
"main_icon_monthCard":{"x":372,"y":344,"w":64,"h":77,"offX":8,"offY":1,"sourceW":78,"sourceH":78},
"main_icon_openServer":{"x":296,"y":339,"w":74,"h":77,"offX":0,"offY":7,"sourceW":74,"sourceH":85},
"main_icon_peaksBattle":{"x":153,"y":175,"w":74,"h":84,"offX":0,"offY":1,"sourceW":74,"sourceH":85},
"main_icon_qixi_activity":{"x":738,"y":1,"w":81,"h":82,"offX":1,"offY":3,"sourceW":82,"sourceH":85},
"main_icon_rank":{"x":608,"y":343,"w":68,"h":77,"offX":4,"offY":8,"sourceW":74,"sourceH":85},
"main_icon_shared":{"x":746,"y":343,"w":64,"h":78,"offX":11,"offY":6,"sourceW":80,"sourceH":84},
"main_icon_shenmi":{"x":695,"y":260,"w":74,"h":81,"offX":0,"offY":6,"sourceW":74,"sourceH":89},
"main_icon_shoucang":{"x":920,"y":260,"w":74,"h":80,"offX":0,"offY":5,"sourceW":74,"sourceH":85},
"main_icon_treasure":{"x":150,"y":345,"w":63,"h":77,"offX":6,"offY":8,"sourceW":74,"sourceH":85},
"main_icon_twkefu":{"x":402,"y":1,"w":82,"h":85,"offX":0,"offY":0,"sourceW":82,"sourceH":85},
"main_icon_vip":{"x":79,"y":346,"w":67,"h":69,"offX":4,"offY":9,"sourceW":78,"sourceH":78},
"main_icon_welfare":{"x":678,"y":343,"w":66,"h":77,"offX":4,"offY":8,"sourceW":74,"sourceH":85},
"main_icon_xp_experencet":{"x":1,"y":201,"w":74,"h":83,"offX":0,"offY":2,"sourceW":74,"sourceH":85},
"main_icon_yaoqing":{"x":950,"y":88,"w":72,"h":85,"offX":1,"offY":0,"sourceW":74,"sourceH":85},
"main_icon_yellow":{"x":874,"y":88,"w":74,"h":85,"offX":0,"offY":0,"sourceW":74,"sourceH":85},
"main_vip6":{"x":798,"y":88,"w":74,"h":85,"offX":0,"offY":0,"sourceW":74,"sourceH":85},
"main_icon_common_activity1":{"x":454,"y":88,"w":74,"h":85,"offX":0,"offY":0,"sourceW":74,"sourceH":85},
"main_icon_common_activity2":{"x":378,"y":88,"w":74,"h":85,"offX":0,"offY":0,"sourceW":74,"sourceH":85},
"main_icon_wbdouble":{"x":318,"y":1,"w":82,"h":85,"offX":0,"offY":0,"sourceW":82,"sourceH":85},
"main_comeback":{"x":226,"y":88,"w":74,"h":85,"offX":0,"offY":0,"sourceW":74,"sourceH":85},
"main_fuli":{"x":150,"y":88,"w":74,"h":85,"offX":0,"offY":0,"sourceW":74,"sourceH":85},
"main_icon_kuanianGift":{"x":722,"y":85,"w":74,"h":85,"offX":0,"offY":0,"sourceW":74,"sourceH":85},
"main_beijing":{"x":646,"y":85,"w":74,"h":85,"offX":0,"offY":0,"sourceW":74,"sourceH":85},
"main_limit_recycle":{"x":570,"y":85,"w":74,"h":85,"offX":0,"offY":0,"sourceW":74,"sourceH":85},
"main_icon_common_activity3":{"x":234,"y":1,"w":82,"h":85,"offX":0,"offY":0,"sourceW":82,"sourceH":85},
"main_icon_activitySprint":{"x":150,"y":1,"w":82,"h":85,"offX":0,"offY":0,"sourceW":82,"sourceH":85},
"main_icon_peaksBattle_cross":{"x":77,"y":175,"w":74,"h":85,"offX":0,"offY":0,"sourceW":74,"sourceH":85},
"main_icon_xyxad":{"x":570,"y":1,"w":82,"h":82,"offX":0,"offY":2,"sourceW":82,"sourceH":85},
"main_icon_xyxios":{"x":654,"y":1,"w":82,"h":82,"offX":0,"offY":2,"sourceW":82,"sourceH":85},
"main_weiduan":{"x":302,"y":88,"w":74,"h":85,"offX":0,"offY":0,"sourceW":74,"sourceH":85},
"main_icon_luckybox":{"x":305,"y":175,"w":80,"h":77,"offX":1,"offY":8,"sourceW":82,"sourceH":85},
"main_icon_molong":{"x":897,"y":1,"w":74,"h":85,"offX":0,"offY":0,"sourceW":74,"sourceH":85},
"main_icon_openServer1":{"x":619,"y":259,"w":74,"h":82,"offX":0,"offY":2,"sourceW":74,"sourceH":85},
"main_icon_openServer2":{"x":821,"y":1,"w":74,"h":85,"offX":0,"offY":0,"sourceW":74,"sourceH":85},
"main_icon_openServer3":{"x":530,"y":172,"w":74,"h":85,"offX":0,"offY":0,"sourceW":74,"sourceH":85},
"main_icon_seven":{"x":834,"y":175,"w":74,"h":83,"offX":0,"offY":2,"sourceW":74,"sourceH":85},
"main_icon_seven1":{"x":758,"y":175,"w":74,"h":83,"offX":0,"offY":2,"sourceW":74,"sourceH":85},
"main_icon_two":{"x":387,"y":175,"w":74,"h":83,"offX":0,"offY":2,"sourceW":74,"sourceH":85},
"main_icon_two1":{"x":305,"y":254,"w":74,"h":83,"offX":0,"offY":2,"sourceW":74,"sourceH":85},
"main_icon_years":{"x":771,"y":260,"w":74,"h":81,"offX":0,"offY":4,"sourceW":74,"sourceH":85},
"main_oneYuanBuy":{"x":1,"y":114,"w":74,"h":85,"offX":0,"offY":0,"sourceW":74,"sourceH":85},
"main_taskFirstRecharge":{"x":1,"y":1,"w":147,"h":111,"offX":0,"offY":0,"sourceW":147,"sourceH":111},
"main_weekcard":{"x":463,"y":175,"w":65,"h":77,"offX":6,"offY":8,"sourceW":74,"sourceH":85},
"main_login":{"x":229,"y":175,"w":74,"h":84,"offX":0,"offY":1,"sourceW":74,"sourceH":85}}}