{"activity_manage_16":{"name":"VIP Lottery","refId":"activity_manage_16"},"activity_manage_17":{"name":"Server Launch Speed Leveling (Limited Time)","refId":"activity_manage_17"},"activity_manage_2":{"name":"7-Day Login","refId":"activity_manage_2"},"activity_manage_3":{"name":"Online Duration Reward","refId":"activity_manage_3"},"activity_manage_5":{"name":"Arena","refId":"activity_manage_5"},"activity_manage_6":{"name":"Monster Invasion","refId":"activity_manage_6"},"activity_manage_7":{"name":"Mining","refId":"activity_manage_7"}}