{"res":{"res3":{"x":242,"y":0,"w":90,"h":134},"res0":{"x":117,"y":132,"w":115,"h":126},"res7":{"x":0,"y":0,"w":127,"h":131},"res1":{"x":128,"y":0,"w":113,"h":131},"res5":{"x":223,"y":259,"w":91,"h":124},"res4":{"x":233,"y":135,"w":84,"h":122},"res6":{"x":0,"y":132,"w":116,"h":139},"res2":{"x":117,"y":259,"w":105,"h":119}},"mc":{"1025_0300_0":{"events":[],"frames":[{"res":"res0","y":-121,"x":-31},{"res":"res1","y":-114,"x":-32},{"res":"res2","y":-102,"x":-41},{"res":"res3","y":-114,"x":-53},{"res":"res4","y":-99,"x":-50},{"res":"res5","y":-101,"x":-38},{"res":"res6","y":-120,"x":-26},{"res":"res7","y":-121,"x":-27}],"labels":[],"frameRate":24}},"scale":1}