{"res":{"res7":{"x":318,"y":338,"w":144,"h":168},"res1":{"x":160,"y":336,"w":157,"h":168},"res5":{"x":0,"y":0,"w":173,"h":166},"res0":{"x":318,"y":172,"w":153,"h":165},"res2":{"x":463,"y":338,"w":142,"h":173},"res6":{"x":0,"y":336,"w":159,"h":167},"res3":{"x":174,"y":0,"w":156,"h":171},"res4":{"x":0,"y":167,"w":171,"h":168}},"mc":{"1051_0200_4":{"labels":[],"frames":[{"res":"res0","y":-140,"x":-77},{"res":"res1","y":-138,"x":-78},{"res":"res2","y":-144,"x":-84},{"res":"res3","y":-146,"x":-90},{"res":"res4","y":-143,"x":-95},{"res":"res5","y":-140,"x":-95},{"res":"res6","y":-144,"x":-86},{"res":"res7","y":-144,"x":-76}],"events":[],"frameRate":24}},"scale":1}