{"res":{"res4":{"x":132,"y":106,"w":61,"h":112},"res2":{"x":66,"y":125,"w":65,"h":84},"res0":{"x":0,"y":0,"w":75,"h":124},"res5":{"x":194,"y":0,"w":56,"h":125},"res3":{"x":0,"y":125,"w":65,"h":87},"res1":{"x":76,"y":0,"w":63,"h":105}},"mc":{"1102_0350_0":{"events":[],"frames":[{"res":"res0","y":-116,"x":-35},{"res":"res1","y":-97,"x":-26},{"res":"res2","y":-76,"x":-26},{"res":"res3","y":-79,"x":-26},{"res":"res4","y":-104,"x":-26},{"res":"res5","y":-117,"x":-25}],"labels":[],"frameRate":24}},"scale":1}