{"res":{"res1":{"x":76,"y":0,"w":66,"h":105},"res0":{"x":0,"y":0,"w":75,"h":124},"res5":{"x":199,"y":0,"w":57,"h":125},"res3":{"x":68,"y":125,"w":66,"h":87},"res2":{"x":0,"y":125,"w":67,"h":84},"res4":{"x":135,"y":106,"w":63,"h":112}},"mc":{"1106_0350_0":{"events":[],"frames":[{"res":"res0","y":-116,"x":-35},{"res":"res1","y":-97,"x":-28},{"res":"res2","y":-76,"x":-27},{"res":"res3","y":-79,"x":-27},{"res":"res4","y":-104,"x":-27},{"res":"res5","y":-117,"x":-26}],"labels":[],"frameRate":24}},"scale":1}