{"res":{"res0":{"x":0,"y":0,"w":75,"h":112},"res2":{"x":76,"y":0,"w":65,"h":93},"res5":{"x":199,"y":0,"w":60,"h":114},"res4":{"x":137,"y":94,"w":61,"h":101},"res3":{"x":71,"y":113,"w":65,"h":92},"res1":{"x":0,"y":113,"w":70,"h":88}},"mc":{"1108_0350_4":{"events":[],"frames":[{"res":"res0","y":-107,"x":-38},{"res":"res1","y":-83,"x":-36},{"res":"res2","y":-71,"x":-39},{"res":"res3","y":-79,"x":-39},{"res":"res4","y":-96,"x":-35},{"res":"res5","y":-105,"x":-31}],"labels":[],"frameRate":24}},"scale":1}