{"res":{"res2":{"x":291,"y":197,"w":84,"h":104},"res5":{"x":199,"y":0,"w":92,"h":96},"res3":{"x":293,"y":0,"w":79,"h":106},"res8":{"x":203,"y":97,"w":89,"h":99},"res7":{"x":104,"y":225,"w":94,"h":98},"res10":{"x":0,"y":113,"w":103,"h":108},"res0":{"x":0,"y":0,"w":104,"h":112},"res1":{"x":291,"y":302,"w":84,"h":105},"res11":{"x":104,"y":113,"w":98,"h":111},"res6":{"x":199,"y":225,"w":91,"h":97},"res4":{"x":105,"y":0,"w":93,"h":103},"res9":{"x":0,"y":222,"w":103,"h":103}},"mc":{"11108_0200_4":{"events":[],"frames":[{"res":"res0","y":-87,"x":-98},{"res":"res1","y":-78,"x":-88},{"res":"res2","y":-75,"x":-87},{"res":"res3","y":-75,"x":-81},{"res":"res4","y":-78,"x":-81},{"res":"res5","y":-77,"x":-75},{"res":"res6","y":-78,"x":-73},{"res":"res7","y":-77,"x":-79},{"res":"res8","y":-79,"x":-83},{"res":"res9","y":-82,"x":-86},{"res":"res10","y":-85,"x":-91},{"res":"res11","y":-90,"x":-95}],"labels":[],"frameRate":24}},"scale":1}