{"res":{"res1":{"x":0,"y":111,"w":120,"h":153},"res4":{"x":148,"y":0,"w":81,"h":82},"res7":{"x":224,"y":83,"w":58,"h":80},"res5":{"x":222,"y":218,"w":68,"h":80},"res3":{"x":121,"y":111,"w":102,"h":106},"res2":{"x":121,"y":218,"w":100,"h":97},"res0":{"x":0,"y":0,"w":147,"h":110},"res6":{"x":0,"y":265,"w":85,"h":71}},"mc":{"11114_0300_0":{"events":[],"frames":[{"res":"res0","y":-95,"x":-17},{"res":"res1","y":-185,"x":7},{"res":"res2","y":-123,"x":-35},{"res":"res3","y":-166,"x":5},{"res":"res4","y":-79,"x":-83},{"res":"res5","y":-79,"x":-72},{"res":"res6","y":-85,"x":-61},{"res":"res7","y":-98,"x":1}],"labels":[],"frameRate":24}},"scale":1}