{"res":{"res6":{"x":205,"y":0,"w":118,"h":108},"res5":{"x":324,"y":0,"w":115,"h":105},"res3":{"x":179,"y":281,"w":166,"h":135},"res7":{"x":181,"y":126,"w":150,"h":116},"res4":{"x":332,"y":106,"w":110,"h":105},"res1":{"x":0,"y":281,"w":178,"h":153},"res0":{"x":0,"y":126,"w":180,"h":154},"res2":{"x":0,"y":0,"w":204,"h":125}},"mc":{"11110_0300_1":{"events":[],"frames":[{"res":"res0","y":-81,"x":-38},{"res":"res1","y":-162,"x":-22},{"res":"res2","y":-142,"x":-190},{"res":"res3","y":-165,"x":-83},{"res":"res4","y":-94,"x":-26},{"res":"res5","y":-95,"x":-26},{"res":"res6","y":-104,"x":-15},{"res":"res7","y":-110,"x":-15}],"labels":[],"frameRate":24}},"scale":1}