{"res":{"res3":{"x":114,"y":0,"w":93,"h":161},"res4":{"x":192,"y":162,"w":92,"h":148},"res5":{"x":96,"y":294,"w":95,"h":146},"res9":{"x":285,"y":164,"w":89,"h":161},"res1":{"x":375,"y":164,"w":84,"h":163},"res0":{"x":285,"y":0,"w":90,"h":163},"res6":{"x":0,"y":0,"w":113,"h":143},"res2":{"x":208,"y":0,"w":69,"h":156},"res8":{"x":0,"y":294,"w":95,"h":156},"res7":{"x":0,"y":144,"w":105,"h":149}},"mc":{"1113_0301_3":{"events":[],"frames":[{"res":"res0","y":-150,"x":-51},{"res":"res1","y":-150,"x":-36},{"res":"res2","y":-145,"x":-37},{"res":"res3","y":-136,"x":-60},{"res":"res4","y":-123,"x":-54},{"res":"res5","y":-121,"x":-38},{"res":"res6","y":-118,"x":-42},{"res":"res7","y":-124,"x":-51},{"res":"res8","y":-132,"x":-56},{"res":"res9","y":-144,"x":-59}],"labels":[],"frameRate":24}},"scale":1}