{"res":{"res8":{"x":212,"y":0,"w":154,"h":140},"res5":{"x":169,"y":366,"w":167,"h":132},"res6":{"x":0,"y":366,"w":168,"h":136},"res0":{"x":337,"y":350,"w":151,"h":104},"res4":{"x":357,"y":141,"w":114,"h":196},"res3":{"x":0,"y":109,"w":210,"h":130},"res7":{"x":0,"y":240,"w":189,"h":125},"res1":{"x":0,"y":0,"w":211,"h":108},"res9":{"x":190,"y":240,"w":166,"h":109},"res2":{"x":472,"y":0,"w":106,"h":184}},"mc":{"11207_0300_3":{"events":[],"frames":[{"res":"res0","y":-112,"x":-64},{"res":"res1","y":-131,"x":-64},{"res":"res2","y":-208,"x":-33},{"res":"res3","y":-193,"x":-110},{"res":"res4","y":-220,"x":-38},{"res":"res5","y":-107,"x":-32},{"res":"res6","y":-104,"x":-26},{"res":"res7","y":-104,"x":-26},{"res":"res8","y":-103,"x":-31},{"res":"res9","y":-89,"x":-53}],"labels":[],"frameRate":24}},"scale":1}