{"res":{"res4":{"x":117,"y":49,"w":79,"h":127},"res1":{"x":0,"y":0,"w":122,"h":48},"res5":{"x":122,"y":177,"w":29,"h":80},"res6":{"x":87,"y":177,"w":34,"h":65},"res9":{"x":47,"y":177,"w":39,"h":57},"res8":{"x":0,"y":177,"w":46,"h":76},"res2":{"x":197,"y":0,"w":75,"h":132},"res3":{"x":0,"y":49,"w":116,"h":110},"res7":{"x":152,"y":177,"w":26,"h":62},"res0":{"x":179,"y":177,"w":25,"h":55}},"mc":{"11204_0300_4":{"events":[],"frames":[{"res":"res0","y":-90,"x":-32},{"res":"res1","y":-83,"x":-56},{"res":"res2","y":-157,"x":0},{"res":"res3","y":-158,"x":-29},{"res":"res4","y":-150,"x":-1},{"res":"res5","y":-89,"x":-33},{"res":"res6","y":-73,"x":-40},{"res":"res7","y":-71,"x":-33},{"res":"res8","y":-77,"x":-54},{"res":"res9","y":-72,"x":-46}],"labels":[],"frameRate":24}},"scale":1}