{"res":{"res4":{"x":169,"y":219,"w":76,"h":63},"res7":{"x":173,"y":69,"w":71,"h":64},"res8":{"x":170,"y":0,"w":74,"h":68},"res6":{"x":0,"y":225,"w":68,"h":61},"res10":{"x":89,"y":75,"w":83,"h":73},"res11":{"x":0,"y":149,"w":87,"h":75},"res5":{"x":174,"y":134,"w":71,"h":62},"res1":{"x":0,"y":75,"w":88,"h":73},"res0":{"x":0,"y":0,"w":89,"h":74},"res3":{"x":88,"y":219,"w":80,"h":66},"res9":{"x":90,"y":0,"w":79,"h":71},"res2":{"x":88,"y":149,"w":85,"h":69}},"mc":{"11203_0200_3":{"events":[],"frames":[{"res":"res0","y":-110,"x":-46},{"res":"res1","y":-107,"x":-46},{"res":"res2","y":-106,"x":-45},{"res":"res3","y":-107,"x":-41},{"res":"res4","y":-107,"x":-37},{"res":"res5","y":-106,"x":-32},{"res":"res6","y":-102,"x":-30},{"res":"res7","y":-102,"x":-33},{"res":"res8","y":-105,"x":-36},{"res":"res9","y":-110,"x":-39},{"res":"res10","y":-113,"x":-42},{"res":"res11","y":-113,"x":-44}],"labels":[],"frameRate":24}},"scale":1}