{"res":{"res2":{"x":207,"y":504,"w":197,"h":130},"res3":{"x":220,"y":0,"w":140,"h":144},"res4":{"x":212,"y":150,"w":194,"h":130},"res8":{"x":0,"y":0,"w":219,"h":149},"res9":{"x":211,"y":322,"w":204,"h":181},"res6":{"x":0,"y":322,"w":210,"h":161},"res0":{"x":407,"y":0,"w":148,"h":218},"res1":{"x":416,"y":219,"w":125,"h":223},"res7":{"x":0,"y":484,"w":206,"h":162},"res5":{"x":0,"y":150,"w":211,"h":171}},"mc":{"11212_0300_1":{"events":[],"frames":[{"res":"res0","y":-180,"x":-40},{"res":"res1","y":-211,"x":-52},{"res":"res2","y":-165,"x":-136},{"res":"res3","y":-163,"x":-80},{"res":"res4","y":-167,"x":-139},{"res":"res5","y":-194,"x":-28},{"res":"res6","y":-192,"x":-22},{"res":"res7","y":-194,"x":-21},{"res":"res8","y":-165,"x":-32},{"res":"res9","y":-172,"x":-36}],"labels":[],"frameRate":24}},"scale":0.8}