{"res":{"res3":{"x":93,"y":137,"w":91,"h":70},"res5":{"x":93,"y":208,"w":82,"h":59},"res2":{"x":185,"y":72,"w":82,"h":76},"res0":{"x":0,"y":137,"w":92,"h":102},"res4":{"x":0,"y":75,"w":105,"h":61},"res1":{"x":0,"y":0,"w":121,"h":74},"res6":{"x":106,"y":75,"w":71,"h":59},"res7":{"x":122,"y":0,"w":89,"h":71}},"mc":{"11307_0300_2":{"events":[],"frames":[{"res":"res0","y":-88,"x":-43},{"res":"res1","y":-96,"x":-39},{"res":"res2","y":-113,"x":18},{"res":"res3","y":-138,"x":11},{"res":"res4","y":-94,"x":-71},{"res":"res5","y":-82,"x":-64},{"res":"res6","y":-81,"x":-61},{"res":"res7","y":-77,"x":-55}],"labels":[],"frameRate":24}},"scale":1}