{"res":{"res4":{"x":0,"y":0,"w":64,"h":121},"res9":{"x":241,"y":0,"w":39,"h":122},"res0":{"x":281,"y":0,"w":34,"h":124},"res3":{"x":127,"y":126,"w":54,"h":125},"res7":{"x":64,"y":122,"w":62,"h":126},"res5":{"x":0,"y":122,"w":63,"h":126},"res6":{"x":127,"y":0,"w":62,"h":125},"res8":{"x":235,"y":125,"w":48,"h":123},"res1":{"x":190,"y":0,"w":50,"h":124},"res2":{"x":182,"y":126,"w":52,"h":125}},"mc":{"1252_0300_3":{"events":[],"frames":[{"res":"res0","y":-115,"x":-17},{"res":"res1","y":-115,"x":-16},{"res":"res2","y":-116,"x":-19},{"res":"res3","y":-116,"x":-24},{"res":"res4","y":-115,"x":-25},{"res":"res5","y":-106,"x":-21},{"res":"res6","y":-105,"x":-21},{"res":"res7","y":-106,"x":-20},{"res":"res8","y":-109,"x":-16},{"res":"res9","y":-113,"x":-13}],"labels":[],"frameRate":24}},"scale":1}