{"res":{"res3":{"x":164,"y":127,"w":46,"h":119},"res1":{"x":0,"y":122,"w":58,"h":120},"res8":{"x":59,"y":122,"w":55,"h":125},"res9":{"x":0,"y":0,"w":59,"h":121},"res0":{"x":112,"y":0,"w":49,"h":118},"res6":{"x":252,"y":0,"w":39,"h":127},"res7":{"x":211,"y":127,"w":40,"h":126},"res4":{"x":115,"y":119,"w":48,"h":122},"res5":{"x":164,"y":0,"w":47,"h":126},"res2":{"x":60,"y":0,"w":51,"h":119}},"mc":{"1253_0300_0":{"events":[],"frames":[{"res":"res0","y":-113,"x":-28},{"res":"res1","y":-114,"x":-42},{"res":"res2","y":-114,"x":-41},{"res":"res3","y":-114,"x":-37},{"res":"res4","y":-117,"x":-39},{"res":"res5","y":-123,"x":-29},{"res":"res6","y":-124,"x":-19},{"res":"res7","y":-123,"x":-22},{"res":"res8","y":-120,"x":-28},{"res":"res9","y":-116,"x":-31}],"labels":[],"frameRate":24}},"scale":1}