{"res":{"res7":{"x":100,"y":0,"w":88,"h":129},"res5":{"x":0,"y":256,"w":89,"h":133},"res6":{"x":266,"y":262,"w":83,"h":131},"res9":{"x":0,"y":129,"w":95,"h":126},"res4":{"x":180,"y":262,"w":85,"h":134},"res3":{"x":90,"y":256,"w":89,"h":129},"res0":{"x":272,"y":0,"w":72,"h":135},"res2":{"x":0,"y":0,"w":99,"h":128},"res8":{"x":189,"y":0,"w":82,"h":127},"res1":{"x":180,"y":130,"w":88,"h":131}},"mc":{"1267_0300_3":{"events":[],"frames":[{"res":"res0","y":-121,"x":-55},{"res":"res1","y":-118,"x":-60},{"res":"res2","y":-116,"x":-62},{"res":"res3","y":-116,"x":-58},{"res":"res4","y":-118,"x":-52},{"res":"res5","y":-113,"x":-48},{"res":"res6","y":-113,"x":-47},{"res":"res7","y":-113,"x":-52},{"res":"res8","y":-115,"x":-58},{"res":"res9","y":-118,"x":-67}],"labels":[],"frameRate":24}},"scale":0.8}