{"res":{"res8":{"x":147,"y":218,"w":67,"h":100},"res11":{"x":0,"y":0,"w":74,"h":112},"res5":{"x":149,"y":0,"w":69,"h":108},"res3":{"x":219,"y":0,"w":55,"h":96},"res2":{"x":215,"y":218,"w":55,"h":100},"res0":{"x":75,"y":0,"w":73,"h":116},"res6":{"x":0,"y":113,"w":74,"h":114},"res7":{"x":75,"y":117,"w":71,"h":106},"res1":{"x":218,"y":109,"w":66,"h":106},"res10":{"x":147,"y":117,"w":70,"h":100},"res4":{"x":0,"y":228,"w":63,"h":95},"res9":{"x":75,"y":224,"w":62,"h":96}},"mc":{"1353_0200_3":{"events":[],"frames":[{"res":"res0","y":-103,"x":-39},{"res":"res1","y":-100,"x":-34},{"res":"res2","y":-101,"x":-26},{"res":"res3","y":-104,"x":-28},{"res":"res4","y":-106,"x":-35},{"res":"res5","y":-105,"x":-41},{"res":"res6","y":-103,"x":-45},{"res":"res7","y":-100,"x":-42},{"res":"res8","y":-101,"x":-35},{"res":"res9","y":-104,"x":-27},{"res":"res10","y":-106,"x":-34},{"res":"res11","y":-106,"x":-38}],"labels":[],"frameRate":24}},"scale":1}