{"res":{"res5":{"x":227,"y":161,"w":75,"h":158},"res2":{"x":0,"y":129,"w":126,"h":122},"res0":{"x":227,"y":0,"w":83,"h":160},"res3":{"x":0,"y":0,"w":130,"h":128},"res1":{"x":127,"y":129,"w":99,"h":150},"res4":{"x":0,"y":252,"w":112,"h":139}},"mc":{"1363_0350_2":{"events":[],"frames":[{"res":"res0","y":-129,"x":-33},{"res":"res1","y":-109,"x":-42},{"res":"res2","y":-89,"x":-57},{"res":"res3","y":-90,"x":-58},{"res":"res4","y":-105,"x":-60},{"res":"res5","y":-133,"x":-46}],"labels":[],"frameRate":24}},"scale":1}