{"res":{"res10":{"x":234,"y":0,"w":210,"h":192},"res8":{"x":449,"y":201,"w":196,"h":217},"res7":{"x":646,"y":201,"w":193,"h":225},"res0":{"x":0,"y":475,"w":228,"h":167},"res11":{"x":0,"y":643,"w":222,"h":180},"res1":{"x":0,"y":310,"w":231,"h":164},"res3":{"x":0,"y":155,"w":232,"h":154},"res6":{"x":442,"y":494,"w":208,"h":217},"res4":{"x":223,"y":643,"w":218,"h":168},"res9":{"x":445,"y":0,"w":202,"h":200},"res2":{"x":0,"y":0,"w":233,"h":154},"res5":{"x":232,"y":310,"w":216,"h":183}},"mc":{"1508_0200_3":{"events":[],"frames":[{"res":"res0","y":-148,"x":-164},{"res":"res1","y":-148,"x":-164},{"res":"res2","y":-148,"x":-162},{"res":"res3","y":-152,"x":-159},{"res":"res4","y":-160,"x":-152},{"res":"res5","y":-159,"x":-152},{"res":"res6","y":-173,"x":-147},{"res":"res7","y":-168,"x":-142},{"res":"res8","y":-162,"x":-146},{"res":"res9","y":-156,"x":-148},{"res":"res10","y":-156,"x":-154},{"res":"res11","y":-156,"x":-160}],"labels":[],"frameRate":24}},"scale":0.8}