{"res":{"res5":{"x":249,"y":0,"w":155,"h":170},"res4":{"x":0,"y":246,"w":200,"h":149},"res2":{"x":201,"y":246,"w":193,"h":129},"res3":{"x":201,"y":376,"w":190,"h":135},"res0":{"x":0,"y":117,"w":214,"h":128},"res1":{"x":0,"y":0,"w":248,"h":116}},"mc":{"1604_0350_1":{"events":[],"frames":[{"res":"res0","y":-144,"x":-129},{"res":"res1","y":-142,"x":-167},{"res":"res2","y":-134,"x":-111},{"res":"res3","y":-142,"x":-96},{"res":"res4","y":-148,"x":-96},{"res":"res5","y":-158,"x":-91}],"labels":[],"frameRate":24}},"scale":1}