{"res":{"res2":{"x":208,"y":0,"w":152,"h":168},"res4":{"x":184,"y":295,"w":167,"h":155},"res3":{"x":352,"y":169,"w":146,"h":174},"res5":{"x":0,"y":295,"w":183,"h":155},"res1":{"x":0,"y":148,"w":190,"h":146},"res0":{"x":0,"y":0,"w":207,"h":147}},"mc":{"1604_0350_2":{"events":[],"frames":[{"res":"res0","y":-159,"x":-170},{"res":"res1","y":-158,"x":-144},{"res":"res2","y":-155,"x":-81},{"res":"res3","y":-154,"x":-73},{"res":"res4","y":-156,"x":-98},{"res":"res5","y":-162,"x":-128}],"labels":[],"frameRate":24}},"scale":1}