{"res":{"res0":{"x":0,"y":94,"w":114,"h":89},"res2":{"x":111,"y":389,"w":109,"h":98},"res6":{"x":327,"y":0,"w":100,"h":131},"res4":{"x":222,"y":206,"w":109,"h":110},"res9":{"x":115,"y":94,"w":109,"h":111},"res3":{"x":0,"y":291,"w":110,"h":100},"res10":{"x":0,"y":184,"w":112,"h":106},"res7":{"x":225,"y":0,"w":101,"h":119},"res5":{"x":331,"y":317,"w":99,"h":125},"res1":{"x":0,"y":0,"w":115,"h":93},"res11":{"x":111,"y":291,"w":110,"h":97},"res8":{"x":222,"y":317,"w":108,"h":119}},"mc":{"1901_0200_3":{"events":[],"frames":[{"res":"res0","y":-119,"x":-68},{"res":"res1","y":-120,"x":-69},{"res":"res2","y":-122,"x":-66},{"res":"res3","y":-126,"x":-69},{"res":"res4","y":-127,"x":-77},{"res":"res5","y":-131,"x":-79},{"res":"res6","y":-132,"x":-82},{"res":"res7","y":-131,"x":-82},{"res":"res8","y":-132,"x":-85},{"res":"res9","y":-132,"x":-80},{"res":"res10","y":-128,"x":-79},{"res":"res11","y":-121,"x":-75}],"labels":[],"frameRate":24}},"scale":1}