{"res":{"res1":{"x":360,"y":0,"w":168,"h":204},"res0":{"x":184,"y":354,"w":175,"h":191},"res5":{"x":0,"y":0,"w":187,"h":162},"res6":{"x":360,"y":205,"w":166,"h":193},"res7":{"x":360,"y":399,"w":137,"h":204},"res3":{"x":188,"y":0,"w":171,"h":196},"res2":{"x":0,"y":163,"w":184,"h":190},"res4":{"x":0,"y":354,"w":183,"h":171}},"mc":{"1907_0300_0":{"events":[],"frames":[{"res":"res0","y":-150,"x":-104},{"res":"res1","y":-166,"x":-112},{"res":"res2","y":-174,"x":-100},{"res":"res3","y":-199,"x":-77},{"res":"res4","y":-166,"x":-81},{"res":"res5","y":-179,"x":-90},{"res":"res6","y":-180,"x":-96},{"res":"res7","y":-177,"x":-100}],"labels":[],"frameRate":24}},"scale":1}