{"res":{"res3":{"x":190,"y":253,"w":172,"h":245},"res2":{"x":0,"y":0,"w":202,"h":252},"res5":{"x":524,"y":0,"w":156,"h":262},"res0":{"x":203,"y":0,"w":171,"h":246},"res4":{"x":363,"y":247,"w":160,"h":247},"res1":{"x":0,"y":253,"w":189,"h":247}},"mc":{"2145_0300_3":{"labels":[],"frames":[{"res":"res0","y":-234,"x":-119},{"res":"res1","y":-231,"x":-67},{"res":"res2","y":-236,"x":-36},{"res":"res3","y":-229,"x":-80},{"res":"res4","y":-231,"x":-76},{"res":"res5","y":-246,"x":-94}],"events":[],"frameRate":24}},"scale":0.8}