{"res":{"res33":{"x":0,"y":877,"w":1,"h":1},"res3":{"x":822,"y":295,"w":53,"h":132},"res30":{"x":657,"y":692,"w":148,"h":221},"res21":{"x":326,"y":0,"w":224,"h":183},"res11":{"x":246,"y":456,"w":180,"h":45},"res7":{"x":0,"y":877,"w":1,"h":1},"res35":{"x":806,"y":692,"w":70,"h":146},"res25":{"x":0,"y":877,"w":1,"h":1},"res2":{"x":0,"y":877,"w":1,"h":1},"res16":{"x":0,"y":877,"w":1,"h":1},"res8":{"x":0,"y":877,"w":1,"h":1},"res10":{"x":0,"y":877,"w":1,"h":1},"res20":{"x":243,"y":592,"w":241,"h":191},"res37":{"x":657,"y":400,"w":164,"h":291},"res15":{"x":0,"y":877,"w":1,"h":1},"res24":{"x":0,"y":877,"w":1,"h":1},"res29":{"x":250,"y":193,"w":228,"h":262},"res32":{"x":0,"y":877,"w":1,"h":1},"res1":{"x":0,"y":877,"w":1,"h":1},"res19":{"x":246,"y":502,"w":147,"h":45},"res36":{"x":703,"y":0,"w":121,"h":294},"res0":{"x":0,"y":877,"w":1,"h":1},"res28":{"x":0,"y":592,"w":242,"h":284},"res9":{"x":0,"y":877,"w":1,"h":1},"res39":{"x":0,"y":877,"w":1,"h":1},"res6":{"x":479,"y":184,"w":223,"h":215},"res18":{"x":0,"y":877,"w":1,"h":1},"res38":{"x":485,"y":579,"w":171,"h":286},"res13":{"x":0,"y":87,"w":306,"h":105},"res34":{"x":0,"y":877,"w":1,"h":1},"res27":{"x":551,"y":0,"w":144,"h":121},"res23":{"x":0,"y":877,"w":1,"h":1},"res14":{"x":243,"y":784,"w":212,"h":109},"res31":{"x":0,"y":877,"w":1,"h":1},"res5":{"x":0,"y":193,"w":249,"h":201},"res4":{"x":0,"y":395,"w":245,"h":196},"res22":{"x":479,"y":400,"w":172,"h":178},"res12":{"x":0,"y":0,"w":325,"h":86},"res17":{"x":0,"y":877,"w":1,"h":1},"res26":{"x":0,"y":877,"w":1,"h":1}},"mc":{"0":{"frameRate":24,"events":[],"frames":[{"y":-422,"res":"res0","x":-422},{"y":-422,"res":"res1","x":-422},{"y":-422,"res":"res2","x":-422},{"y":-108,"res":"res3","x":-86},{"y":-170,"res":"res4","x":-49},{"y":-152,"res":"res5","x":-55},{"y":-152,"res":"res6","x":-55},{"y":-422,"res":"res7","x":-422}],"labels":[]},"1":{"frameRate":24,"events":[],"frames":[{"y":-422,"res":"res8","x":-422},{"y":-422,"res":"res9","x":-422},{"y":-422,"res":"res10","x":-422},{"y":-82,"res":"res11","x":-108},{"y":-112,"res":"res12","x":-224},{"y":-111,"res":"res13","x":-206},{"y":-111,"res":"res14","x":-112},{"y":-422,"res":"res15","x":-422}],"labels":[]},"2":{"frameRate":24,"events":[],"frames":[{"y":-422,"res":"res16","x":-422},{"y":-422,"res":"res17","x":-422},{"y":-422,"res":"res18","x":-422},{"y":-109,"res":"res19","x":-70},{"y":-187,"res":"res20","x":-105},{"y":-178,"res":"res21","x":-89},{"y":-173,"res":"res22","x":-37},{"y":-422,"res":"res23","x":-422}],"labels":[]},"3":{"frameRate":24,"events":[],"frames":[{"y":-422,"res":"res24","x":-422},{"y":-422,"res":"res25","x":-422},{"y":-422,"res":"res26","x":-422},{"y":-147,"res":"res27","x":-77},{"y":-236,"res":"res28","x":-121},{"y":-215,"res":"res29","x":-107},{"y":-174,"res":"res30","x":-27},{"y":-422,"res":"res31","x":-422}],"labels":[]},"4":{"frameRate":24,"events":[],"frames":[{"y":-422,"res":"res32","x":-422},{"y":-422,"res":"res33","x":-422},{"y":-422,"res":"res34","x":-422},{"y":-139,"res":"res35","x":-65},{"y":-208,"res":"res36","x":-75},{"y":-202,"res":"res37","x":-75},{"y":-197,"res":"res38","x":-75},{"y":-422,"res":"res39","x":-422}],"labels":[]}},"scale":0.7}