{"mc":{"6354":{"events":[],"frames":[{"x":-120,"y":-124,"res":"res0"},{"x":-119,"y":-120,"res":"res1"},{"x":-116,"y":-118,"res":"res2"},{"x":-113,"y":-118,"res":"res3"},{"x":-112,"y":-120,"res":"res4"},{"x":-112,"y":-121,"res":"res5"},{"x":-111,"y":-121,"res":"res6"},{"x":-112,"y":-122,"res":"res7"},{"x":-112,"y":-116,"res":"res8"},{"x":-113,"y":-116,"res":"res9"},{"x":-115,"y":-117,"res":"res10"},{"x":-117,"y":-120,"res":"res11"}],"labels":[],"frameRate":24}},"scale":0.8,"res":{"res10":{"x":230,"y":453,"w":225,"h":217},"res2":{"x":0,"y":453,"w":229,"h":226},"res1":{"x":0,"y":227,"w":231,"h":225},"res4":{"x":456,"y":452,"w":224,"h":229},"res9":{"x":233,"y":0,"w":223,"h":216},"res11":{"x":0,"y":680,"w":229,"h":221},"res6":{"x":681,"y":230,"w":223,"h":226},"res8":{"x":456,"y":682,"w":223,"h":215},"res3":{"x":230,"y":671,"w":225,"h":226},"res7":{"x":232,"y":227,"w":224,"h":224},"res0":{"x":0,"y":0,"w":232,"h":226},"res5":{"x":457,"y":0,"w":224,"h":229}}}