{"res":{"res0":{"x":660,"y":707,"w":190,"h":107},"res2":{"x":0,"y":693,"w":334,"h":204},"res4":{"x":0,"y":0,"w":390,"h":248},"res8":{"x":381,"y":249,"w":368,"h":213},"res5":{"x":378,"y":470,"w":374,"h":236},"res3":{"x":391,"y":0,"w":365,"h":238},"res7":{"x":0,"y":249,"w":380,"h":220},"res1":{"x":335,"y":707,"w":324,"h":183},"res6":{"x":0,"y":470,"w":377,"h":222}},"mc":{"6378":{"frames":[{"res":"res0","y":-51.5,"x":-83},{"res":"res1","y":-88.5,"x":-150},{"res":"res2","y":-99.5,"x":-157},{"res":"res3","y":-112.5,"x":-183},{"res":"res4","y":-111.5,"x":-195},{"res":"res5","y":-111.5,"x":-186},{"res":"res6","y":-104.5,"x":-187},{"res":"res7","y":-101.5,"x":-188},{"res":"res8","y":-95.5,"x":-181}],"labels":[],"frameRate":24,"events":[]}},"scale":0.6}