{"scale":1,"shakeEndFrame":0,"res":{"res1":{"x":0,"y":0,"w":485,"h":703},"res0":{"x":841,"y":336,"w":131,"h":406},"res4":{"x":481,"y":704,"w":359,"h":302},"res3":{"x":0,"y":704,"w":480,"h":307},"res5":{"x":486,"y":336,"w":335,"h":310},"res2":{"x":486,"y":0,"w":481,"h":335}},"mc":{"6388":{"frameRate":24,"events":[],"frames":[{"y":-597,"res":"res0","x":-81},{"y":-594,"res":"res1","x":-234},{"y":-276,"res":"res2","x":-231},{"y":-248,"res":"res3","x":-231},{"y":-251,"res":"res4","x":-160},{"y":-263,"res":"res5","x":-173}],"labels":[]}},"fires":[]}